CHANGELOG
LICENSE
MANIFEST.in
README.md
requirements.txt
setup.py
kunyu/.DS_Store
kunyu/CDN-Discovery.log
kunyu/__init__.py
kunyu/console.py
kunyu/createfinger.py
kunyu.egg-info/PKG-INFO
kunyu.egg-info/SOURCES.txt
kunyu.egg-info/dependency_links.txt
kunyu.egg-info/entry_points.txt
kunyu.egg-info/requires.txt
kunyu.egg-info/top_level.txt
kunyu/config/.DS_Store
kunyu/config/__init__.py
kunyu/config/__version__.py
kunyu/config/setting.py
kunyu/core/PupilMain.py
kunyu/core/__init__.py
kunyu/core/console.py
kunyu/core/crash.py
kunyu/core/createmap.py
kunyu/core/rule.py
kunyu/core/scanalive.py
kunyu/core/seebug.py
kunyu/core/zoomeye.py
kunyu/lib/.DS_Store
kunyu/lib/ExportHandler.py
kunyu/lib/GlobalVariable.py
kunyu/lib/SerachData.py
kunyu/lib/TrackUrl.py
kunyu/lib/__init__.py
kunyu/lib/batchfile.py
kunyu/lib/encode.py
kunyu/lib/export.py
kunyu/lib/grab_beacon_config.nse
kunyu/lib/ipLookUpHelper.py
kunyu/lib/cdn/Darwin
kunyu/lib/cdn/linux
kunyu/lib/cdn/windows.exe
kunyu/pocs/20190404_WEB_Confluence_path_traversal.py
kunyu/pocs/20210923_WEB_Vmware_vCenter_Server_FIleUpload_CVE-2021-22005.py
kunyu/pocs/20211008_web_apache-httpd_dir-traversal-rce_cve-2021-41773_cve-2021-42013.py
kunyu/pocs/__init__.py
kunyu/pocs/demo_poc.py
kunyu/pocs/drupalgeddon2.py
kunyu/pocs/ecshop_rce.py
kunyu/pocs/ftp_burst.py
kunyu/pocs/libssh_auth_bypass.py
kunyu/pocs/node_red_unauthorized_rce.py
kunyu/pocs/redis_unauthorized_access.py
kunyu/pocs/ssh_burst.py
kunyu/pocs/telnet_burst.py
kunyu/pocs/thinkphp_rce.py
kunyu/pocs/thinkphp_rce2.py
kunyu/pocs/wd_nas_login_bypass_rce.py
kunyu/pocs/weblogic_cve_2017_10271_unserialization.py
kunyu/rule/kx-2021-01.yaml
kunyu/rule/kx-2021-02.yaml
kunyu/rule/kx-2022-03.yaml
kunyu/rule/kx-2022-04.yaml
kunyu/rule/kx-2022-05.yaml
kunyu/utils/__init__.py
kunyu/utils/convert.py
kunyu/utils/log.py
kunyu/utils/readineng.py
kunyu/utils/tables.py