Metadata-Version: 2.1
Name: kunyu
Version: 2.1
Summary: kunyu is Cyberspace Resources Surveying and Mapping auxiliary tools
Home-page: 
Author: 风起 <onlyzaliks@gmail.com>
Keywords: Cyberspace Resources,zoomeye,kunyu
Classifier: Development Status :: 5 - Production/Stable
Classifier: Intended Audience :: Developers
Classifier: License :: OSI Approved :: MIT License
Classifier: Natural Language :: English
Classifier: Operating System :: OS Independent
Classifier: Programming Language :: Python :: 3
Classifier: Programming Language :: Python :: 3.5
Classifier: Programming Language :: Python :: 3.6
Classifier: Programming Language :: Python :: 3.7
Classifier: Programming Language :: Python :: 3.8
Classifier: Programming Language :: Python :: 3.9
Classifier: Programming Language :: Python :: 3.10
Classifier: Programming Language :: Python :: 3.11
Classifier: Programming Language :: Python :: 3.12
Classifier: Topic :: Software Development :: Libraries :: Python Modules
License-File: LICENSE
Requires-Dist: mmh3
Requires-Dist: lxml
Requires-Dist: lxml_html_clean
Requires-Dist: pyyaml==5.3.1
Requires-Dist: requests
Requires-Dist: tld
Requires-Dist: xlwt
Requires-Dist: grequests==0.6.0
Requires-Dist: rich==11.0.0
Requires-Dist: python-nmap==0.7.1
Requires-Dist: colorama
Requires-Dist: pocsuite3
Requires-Dist: colorlog
Requires-Dist: setuptools
Requires-Dist: pyee==11.0.1
Requires-Dist: urllib3==1.26.20
Requires-Dist: beautifulsoup4
Requires-Dist: requests-html
Requires-Dist: bs4
Requires-Dist: websockets==10.2
